threadsafe_tkinter/LICENSE.TXT
threadsafe_tkinter/__init__.py
threadsafe_tkinter-1.0.4.dist-info/LICENSE.TXT
threadsafe_tkinter-1.0.4.dist-info/METADATA
threadsafe_tkinter-1.0.4.dist-info/WHEEL
threadsafe_tkinter-1.0.4.dist-info/top_level.txt
threadsafe_tkinter-1.0.4.dist-info/zip-safe
threadsafe_tkinter-1.0.4.dist-info/RECORD
